shreyas_venv/BANK.py
shreyas_venv/__init__.py
kingsgreyas29bank-0.1.dist-info/METADATA
kingsgreyas29bank-0.1.dist-info/WHEEL
kingsgreyas29bank-0.1.dist-info/top_level.txt
kingsgreyas29bank-0.1.dist-info/RECORD
