Metadata-Version: 2.1
Name: kingsgreyas29bank
Version: 0.1
Requires-Dist: numpy
